search_engines/__init__.py
search_engines/config.py
search_engines/engine.py
search_engines/http_client.py
search_engines/multiple_search_engines.py
search_engines/output.py
search_engines/results.py
search_engines/utils.py
search_engines/engines/__init__.py
search_engines/engines/aol.py
search_engines/engines/ask.py
search_engines/engines/bing.py
search_engines/engines/brave.py
search_engines/engines/dogpile.py
search_engines/engines/duckduckgo.py
search_engines/engines/google.py
search_engines/engines/metager.py
search_engines/engines/mojeek.py
search_engines/engines/qwant.py
search_engines/engines/startpage.py
search_engines/engines/torch.py
search_engines/engines/yahoo.py
search_engines/libs/__init__.py
search_engines/libs/get_terminal_size.py
search_engines/libs/windows_cmd_encoding.py
search_engines/search_results/__init__.py
trava_search_engine-0.5.dist-info/LICENSE
trava_search_engine-0.5.dist-info/METADATA
trava_search_engine-0.5.dist-info/WHEEL
trava_search_engine-0.5.dist-info/top_level.txt
trava_search_engine-0.5.dist-info/RECORD
